openneuro/__init__.py
openneuro/_cli.py
openneuro/_config.py
openneuro/_download.py
openneuro/py.typed
openneuro/tests/conftest.py
openneuro/tests/test_config.py
openneuro/tests/test_download.py
openneuro_py-2026.1.0.dist-info/METADATA
openneuro_py-2026.1.0.dist-info/WHEEL
openneuro_py-2026.1.0.dist-info/entry_points.txt
openneuro_py-2026.1.0.dist-info/licenses/LICENSE
openneuro_py-2026.1.0.dist-info/RECORD
