Metadata-Version: 2.4
Name: openneuro-py
Version: 2026.1.0
Summary: A Python client for OpenNeuro.
Project-URL: homepage, https://github.com/hoechenberger/openneuro-py
Author-email: Richard Höchenberger <richard.hoechenberger@gmail.com>
License:                     GNU GENERAL PUBLIC LICENSE
License-File: LICENSE
Keywords: neuroscience,science
Classifier: Intended Audience :: Science/Research
Classifier: Programming Language :: Python
Requires-Python: >=3.10
Requires-Dist: aiofiles
Requires-Dist: httpx>=0.15
Requires-Dist: platformdirs
Requires-Dist: requests
Requires-Dist: sgqlc
Requires-Dist: tqdm
Requires-Dist: typer-slim[standard]>=0.16
